huzzleup.py
huzzleup-0.1.dist-info/METADATA
huzzleup-0.1.dist-info/WHEEL
huzzleup-0.1.dist-info/top_level.txt
huzzleup-0.1.dist-info/RECORD
